.pdfalyzer.example
CHANGELOG.md
LICENSE
pdfalyzer/__init__.py
pdfalyzer/__main__.py
pdfalyzer/binary/binary_scanner.py
pdfalyzer/config.py
pdfalyzer/decorators/document_model_printer.py
pdfalyzer/decorators/indeterminate_node.py
pdfalyzer/decorators/pdf_file.py
pdfalyzer/decorators/pdf_object_properties.py
pdfalyzer/decorators/pdf_tree_node.py
pdfalyzer/decorators/pdf_tree_verifier.py
pdfalyzer/detection/constants/binary_regexes.py
pdfalyzer/detection/constants/javascript_reserved_keywords.py
pdfalyzer/detection/javascript_hunter.py
pdfalyzer/detection/yaralyzer_helper.py
pdfalyzer/font_info.py
pdfalyzer/output/character_mapping.py
pdfalyzer/output/highlighter.py
pdfalyzer/output/layout.py
pdfalyzer/output/pdfalyzer_presenter.py
pdfalyzer/output/tables/decoding_stats_table.py
pdfalyzer/output/tables/pdf_node_rich_table.py
pdfalyzer/output/theme.py
pdfalyzer/pdf_object_relationship.py
pdfalyzer/pdfalyzer.py
pdfalyzer/util/adobe_strings.py
pdfalyzer/util/argument_parser.py
pdfalyzer/util/cli_tools/argument_parsers.py
pdfalyzer/util/cli_tools/page_range.py
pdfalyzer/util/constants.py
pdfalyzer/util/exceptions.py
pdfalyzer/util/helpers/collections_helper.py
pdfalyzer/util/helpers/filesystem_helper.py
pdfalyzer/util/helpers/image_helper.py
pdfalyzer/util/helpers/number_helper.py
pdfalyzer/util/helpers/pdf_object_helper.py
pdfalyzer/util/helpers/rich_helper.py
pdfalyzer/util/helpers/string_helper.py
pdfalyzer/util/logging.py
pdfalyzer/util/output_section.py
pdfalyzer/util/pdf_parser_manager.py
pdfalyzer/yara_rules/PDF.yara
pdfalyzer/yara_rules/PDF_binary_stream.yara
pdfalyzer/yara_rules/__init.py__
pdfalyzer/yara_rules/didier_stevens.yara
pdfalyzer/yara_rules/lprat.static_file_analysis.yara
pdfalyzer/yara_rules/pdf_malware.yara
pdfalyzer-1.19.5.dist-info/LICENSE
pdfalyzer-1.19.5.dist-info/METADATA
pdfalyzer-1.19.5.dist-info/WHEEL
pdfalyzer-1.19.5.dist-info/entry_points.txt
pdfalyzer-1.19.5.dist-info/RECORD
