Metadata-Version: 2.1
Name: pdfalyzer
Version: 1.19.5
Summary: Analyze PDFs with colors (and YARA). Visualize a PDF's inner tree-like data structure, check it against a library of YARA rules, force decodes of suspicious font binaries, and more.
Home-page: https://github.com/michelcrypt4d4mus/pdfalyzer
License: GPL-3.0-or-later
Keywords: ascii art,binary,color,cybersecurity,DFIR,encoding,font,infosec,maldoc,malicious pdf,malware,malware analysis,pdf,pdfs,pdf analysis,pypdf,threat assessment,threat hunting,threat intelligence,threat research,threatintel,visualization,yara
Author: Michel de Cryptadamus
Author-email: michel@cryptadamus.com
Requires-Python: >=3.11,<4.0
Classifier: Development Status :: 5 - Production/Stable
Classifier: Environment :: Console
Classifier: Intended Audience :: Information Technology
Classifier: License :: OSI Approved :: GNU General Public License v3 or later (GPLv3+)
Classifier: Programming Language :: Python
Classifier: Programming Language :: Python :: 3
Classifier: Programming Language :: Python :: 3.11
Classifier: Programming Language :: Python :: 3.12
Classifier: Programming Language :: Python :: 3.13
Classifier: Topic :: Artistic Software
Classifier: Topic :: Scientific/Engineering :: Visualization
Classifier: Topic :: Security
Provides-Extra: extract
Provides-Extra: img
Requires-Dist: PyMuPDF (>=1.26.5,<2.0.0) ; extra == "extract"
Requires-Dist: anytree (>=2.13,<3.0)
Requires-Dist: cairosvg (>=2.8.2,<3.0.0) ; extra == "img"
Requires-Dist: cryptography (>=46.0.3,<47.0.0) ; extra == "extract"
Requires-Dist: pypdf (==6.6.0)
Requires-Dist: pytesseract (>=0.3.13,<0.4.0) ; extra == "extract"
Requires-Dist: requests (>=2,<3) ; extra == "extract"
Requires-Dist: yaralyzer (==1.3.15)
Project-URL: Changelog, https://github.com/michelcrypt4d4mus/pdfalyzer/blob/master/CHANGELOG.md
Project-URL: Documentation, https://github.com/michelcrypt4d4mus/pdfalyzer
Project-URL: Repository, https://github.com/michelcrypt4d4mus/pdfalyzer
